simple_spell_checker/__init__.py
simple_spell_checker/spell_checker.py
simple_spell_checker-0.0.2.dist-info/LICENSE
simple_spell_checker-0.0.2.dist-info/WHEEL
simple_spell_checker-0.0.2.dist-info/METADATA
simple_spell_checker-0.0.2.dist-info/RECORD
