Metadata-Version: 2.1
Name: simple-spell-checker
Version: 0.0.2
Summary: Simple Spell Checker is a spell checker based on prefix tree search. It find nearest to input word from known words (from input list). The algorithm finds mistakes in a word (insertions, deletions, replacements).
Author: Tetiana Lytvynenko
Author-email: lytvynenkotv@gmail.com
Requires-Python: >=3.9,<4.0
Classifier: Programming Language :: Python :: 3
Classifier: Programming Language :: Python :: 3.9
Classifier: Programming Language :: Python :: 3.10
Classifier: Programming Language :: Python :: 3.11
Requires-Dist: fuzzy-multi-dict (>=0.0.4,<0.0.5)
